PyBurprestapi/__init__.py
PyBurprestapi/burpscanner.py
PyBurprestapi-0.1.dist-info/DESCRIPTION.rst
PyBurprestapi-0.1.dist-info/METADATA
PyBurprestapi-0.1.dist-info/RECORD
PyBurprestapi-0.1.dist-info/WHEEL
PyBurprestapi-0.1.dist-info/metadata.json
PyBurprestapi-0.1.dist-info/top_level.txt
PyBurprestapi-0.1.dist-info/zip-safe
