Metadata-Version: 2.0
Name: PyBurprestapi
Version: 0.1
Summary: Python library enumerating the Burp RESTFul API endpoints.
Home-page: https://github.com/anandtiwarics/python-burp-rest-api/
Author: Anand Tiwari
Author-email: anandtiwarics@gmail.com
License: MIT License
Download-URL: https://github.com/anandtiwarics/python-burp-rest-api/releases/download/v0.0.1/burprestapi-0.0.1.tar.gz
Keywords: PyBurprestapi,api,security,software,burp
Platform: UNKNOWN
Classifier: Intended Audience :: Developers
Classifier: Natural Language :: English
Classifier: License :: OSI Approved :: MIT License
Classifier: Topic :: Software Development
Classifier: Topic :: Software Development :: Libraries :: Python Modules
Classifier: Programming Language :: Python
Requires-Dist: requests
